{
    "dark_minimal": {
        "background": "black",
        "foreground": "#0e0e0e",
        "text-color": "white",
        "text-inactive-opacity": 0.5,
        "color-on-accent-light": "black",
        "color-on-accent-dark": "white"
    },
    "light_minimal": {
        "background": "white",
        "foreground": "#ededed",
        "text-color": "black",
        "text-inactive-opacity": 0.5,
        "color-on-accent-light": "black",
        "color-on-accent-dark": "white",
        "accent-inline": "#eb34a4"
    },
    "debug_theme": {
        "background": "#4f4f4f",
        "text-color": "blue",
        "navbar-color": "red",
        "navbar-text-color": "green",
        "title-bar-color": "purple",
        "title-bar-text-color": "orange",
        "bottom-bar-color": "magenta",
        "bottom-bar-text-color": "pink",
        "file-color": "green",
        "file-text-color": "white",
        "location-color": "yellow",
        "location-text-color": "cyan",
        "foreground": "brown",
        "text-inactive-opacity": 0.5,
        "color-on-accent-light": "white",
        "search-bar-color": "red",
        "search-bar-text-color": "green",
        "search-bar-icon-color": "red",
        "color-on-accent-dark": "black",
        "frame-background-override": "green",
        "frame-icon-color-override": "orange",
        "accent-inline": "red",
        "window-border-radius": "10px"
    },
    "!selected": "debug_theme"
}